Sequence_1011_detector.v
module Sequence_detector(clk, rst, data_in, detect);

    input clk,rst,data_in;
    output reg [1:0] detect;

    parameter S0 = 2'b00;
    parameter S1 = 2'b01;
    parameter S2 = 2'b10;
    parameter S3 = 2'b11;

    reg [1:0] state, next_state;

    always @(posedge clk or negedge rst) begin

        if (rst == 1'b1) begin
            state   <= S0;
            detect  <= 2'b00;
        end
        else
            state <= next_state;
    end

    always @(*) begin
        next_state = state;
        case (state) 

            S0: begin
                if (data_in == 1'b1) begin
                    next_state  <= S1;
                    detect      <=2'b00;
                end
                else begin
                    next_state  <= S0;
                    detect      <= 2'b00;
                end
            end

            S1: begin
                if (data_in == 1'b1) begin
                    next_state  <= S1;
                    detect      <=2'b00;
                end
                else begin
                    next_state  <= S2;
                    detect      <= 2'b00;
                end
            end

            S2: begin
                if (data_in == 1'b1) begin
                    next_state  <= S3;
                    detect      <=2'b00;
                end
                else begin
                    next_state  <= S0;
                    detect      <= 2'b00;
                end
            end

            S3: begin
                if (data_in == 1'b1) begin
                    next_state  <= S1;
                    detect      <=2'b01;
                end
                else begin
                    next_state  <= S2;
                    detect      <= 2'b00;
                end
            end

        endcase

    end

endmodule

Sequence_detector_tb.v
module Sequence_detector_tb;

    reg clk, rst, data_in;
    wire [1:0] detect;

    Sequence_detector dut_1011(
        .clk(clk), 
        .rst(rst), 
        .data_in(data_in), 
        .detect(detect)
    );


    always #5 clk=~clk;

    initial begin
        $dumpfile("Sequence_detector.vcd");
        $dumpvars(0);
    end

    initial begin

        clk = 1'b0;
        rst = 1'b1;
        #10
        rst = 1'b0;
        data_in = 1'b1; #10
        data_in = 1'b0; #10
        data_in = 1'b1; #10
        data_in = 1'b1; #10
        data_in = 1'b0; #10
        data_in = 1'b0; #10
        data_in = 1'b1; #10
        data_in = 1'b0; #10
        data_in = 1'b1; #10
        data_in = 1'b1; #10
        data_in = 1'b0; #10
        data_in = 1'b1; #10
        data_in = 1'b1; #10
        #10
        $finish;
    end

endmodule

Sequence_detector.vcd
$date
	Tue Mar 17 19:50:03 2026
$end
$version
	Icarus Verilog
$end
$timescale
	1s
$end
$scope module Sequence_detector_tb $end
$var wire 2 ! detect [1:0] $end
$var reg 1 " clk $end
$var reg 1 # data_in $end
$var reg 1 $ rst $end
$scope module dut_1011 $end
$var wire 1 " clk $end
$var wire 1 # data_in $end
$var wire 1 $ rst $end
$var parameter 2 % S0 $end
$var parameter 2 & S1 $end
$var parameter 2 ' S2 $end
$var parameter 2 ( S3 $end
$var reg 2 ) detect [1:0] $end
$var reg 2 * next_state [1:0] $end
$var reg 2 + state [1:0] $end
$upscope $end
$upscope $end
$enddefinitions $end
$comment Show the parameter values. $end
$dumpall
b11 (
b10 '
b1 &
b0 %
$end
#0
$dumpvars
bx +
bx *
bx )
1$
x#
0"
bx !
$end
#5
b0 *
b0 !
b0 )
b0 +
1"
#10
b1 *
0"
1#
0$
#15
b1 +
1"
#20
b10 *
0"
0#
#25
b0 *
b10 +
1"
#30
b11 *
0"
1#
#35
b1 !
b1 )
b1 *
b11 +
1"
#40
0"
#45
b0 !
b0 )
b1 +
1"
#50
b10 *
0"
0#
#55
b0 *
b10 +
1"
#60
0"
#65
b0 +
1"
#70
b1 *
0"
1#
#75
b1 +
1"
#80
b10 *
0"
0#
#85
b0 *
b10 +
1"
#90
b11 *
0"
1#
#95
b1 !
b1 )
b1 *
b11 +
1"
#100
0"
#105
b0 !
b0 )
b1 +
1"
#110
b10 *
0"
0#
#115
b0 *
b10 +
1"
#120
b11 *
0"
1#
#125
b1 !
b1 )
b1 *
b11 +
1"
#130
0"
#135
b0 !
b0 )
b1 +
1"
